kk_scene_wrapper/__init__.py
kk_scene_wrapper/models.py
kk_scene_wrapper/utils.py
kk_scene_wrapper-0.4.0.dist-info/METADATA
kk_scene_wrapper-0.4.0.dist-info/WHEEL
kk_scene_wrapper-0.4.0.dist-info/RECORD
