Metadata-Version: 2.3
Name: kk_scene_wrapper
Version: 0.4.0
Summary: A wrapper for KK scene management
Author: AX-MMD
Author-email: ax.mmd.yt@gmail.com
Requires-Python: >=3.10,<3.14
Classifier: Programming Language :: Python :: 3
Classifier: Programming Language :: Python :: 3.10
Classifier: Programming Language :: Python :: 3.11
Classifier: Programming Language :: Python :: 3.12
Classifier: Programming Language :: Python :: 3.13
